dim_for_python-0.2.4.dist-info/METADATA
dim_for_python-0.2.4.dist-info/WHEEL
dim_for_python-0.2.4.dist-info/licenses/LICENSE
dim_python/__init__.py
dim_python/__init__.pyi
dim_python/py.typed
dim_python/dim_python.cpython-311-darwin.so
dim_for_python-0.2.4.dist-info/RECORD
