Metadata-Version: 2.4
Name: dim-for-python
Version: 0.2.4
Classifier: Programming Language :: Rust
Classifier: Programming Language :: Python :: Implementation :: CPython
Classifier: Programming Language :: Python :: Implementation :: PyPy
Requires-Dist: pillow >=10.4.0
License-File: LICENSE
Summary: Vectorization with LLMs for Python
Author: Xinyu Bao <baoxinyuworks@163.com>
Author-email: Xinyu Bao <baoxinyuworks@163.com>
Requires-Python: >=3.8
Project-URL: Source Code, https://github.com/AspadaX/dim-python
